tox_backtocks/__init__.py
tox_backtocks/backquote.py
tox_backtocks/setenv.py
tox_backtocks-0.4.0.dist-info/LICENSE
tox_backtocks-0.4.0.dist-info/METADATA
tox_backtocks-0.4.0.dist-info/WHEEL
tox_backtocks-0.4.0.dist-info/entry_points.txt
tox_backtocks-0.4.0.dist-info/RECORD
