Metadata-Version: 2.1
Name: tox-backtocks
Version: 0.4.0
Summary: 
Home-page: https://github.com/Anvil/tox-backtocks/
License: LGPL-2.1-or-later
Keywords: tox,backtocks,backticks,backquotes
Author: Damien Nadé
Author-email: anvil.github+tox-backtocks@livna.org
Requires-Python: >=3.10,<4.0
Classifier: Development Status :: 4 - Beta
Classifier: Environment :: Console
Classifier: Framework :: tox
Classifier: Intended Audience :: Developers
Classifier: License :: OSI Approved
Classifier: Operating System :: OS Independent
Classifier: Programming Language :: Python
Classifier: Programming Language :: Python :: 3
Classifier: Programming Language :: Python :: 3.10
Classifier: Programming Language :: Python :: 3.11
Classifier: Programming Language :: Python :: 3 :: Only
Classifier: Programming Language :: Python :: 3.10
Classifier: Programming Language :: Python :: 3.11
Classifier: Topic :: Software Development :: Quality Assurance
Classifier: Topic :: Software Development :: Testing
Requires-Dist: tox (>=4.4)
Project-URL: Documentation, https://github.com/Anvil/tox-backtocks/
Project-URL: Repository, https://github.com/Anvil/tox-backtocks/
